{
    "steps": [
        {
			"fanSpeed": 9,
			"targetTemp": 186,
			"sectionTime": 9
		},
		{
			"fanSpeed": 9,
			"targetTemp": 189,
			"sectionTime": 9
		},
		{
			"fanSpeed": 9,
			"targetTemp": 192,
			"sectionTime": 9
		},
		{
			"fanSpeed": 9,
			"targetTemp": 196,
			"sectionTime": 9
		},
		{
			"fanSpeed": 9,
			"targetTemp": 199,
			"sectionTime": 9
		},
		{
			"fanSpeed": 9,
			"targetTemp": 202,
			"sectionTime": 9
		},
		{
			"fanSpeed": 9,
			"targetTemp": 206,
			"sectionTime": 9
		},
		{
			"fanSpeed": 9,
			"targetTemp": 209,
			"sectionTime": 9
		},
		{
			"fanSpeed": 9,
			"targetTemp": 212,
			"sectionTime": 9
		},
		{
			"fanSpeed": 9,
			"targetTemp": 215,
			"sectionTime": 9
		},
		{
			"fanSpeed": 9,
			"targetTemp": 219,
			"sectionTime": 9
		},
		{
			"fanSpeed": 9,
			"targetTemp": 223,
			"sectionTime": 9
		},
		{
			"fanSpeed": 9,
			"targetTemp": 227,
			"sectionTime": 9
		},
		{
			"fanSpeed": 9,
			"targetTemp": 232,
			"sectionTime": 9
		},
		{
			"fanSpeed": 9,
			"targetTemp": 236,
			"sectionTime": 9
		},
		{
			"fanSpeed": 9,
			"targetTemp": 240,
			"sectionTime": 9
		},
		{
			"fanSpeed": 9,
			"targetTemp": 245,
			"sectionTime": 9
		},
		{
			"fanSpeed": 9,
			"targetTemp": 249,
			"sectionTime": 9
		},
		{
			"fanSpeed": 8,
			"targetTemp": 253,
			"sectionTime": 9
		},
		{
			"fanSpeed": 8,
			"targetTemp": 257,
			"sectionTime": 9
		},
		{
			"fanSpeed": 8,
			"targetTemp": 262,
			"sectionTime": 9
		},
		{
			"fanSpeed": 8,
			"targetTemp": 266,
			"sectionTime": 9
		},
		{
			"fanSpeed": 8,
			"targetTemp": 269,
			"sectionTime": 9
		},
		{
			"fanSpeed": 8,
			"targetTemp": 275,
			"sectionTime": 9
		},
		{
			"fanSpeed": 8,
			"targetTemp": 279,
			"sectionTime": 9
		},
		{
			"fanSpeed": 8,
			"targetTemp": 283,
			"sectionTime": 9
		},
		{
			"fanSpeed": 8,
			"targetTemp": 288,
			"sectionTime": 9
		},
		{
			"fanSpeed": 7,
			"targetTemp": 292,
			"sectionTime": 9
		},
		{
			"fanSpeed": 7,
			"targetTemp": 296,
			"sectionTime": 9
		},
		{
			"fanSpeed": 7,
			"targetTemp": 300,
			"sectionTime": 9
		},
		{
			"fanSpeed": 7,
			"targetTemp": 305,
			"sectionTime": 9
		},
		{
			"fanSpeed": 7,
			"targetTemp": 308,
			"sectionTime": 9
		},
		{
			"fanSpeed": 7,
			"targetTemp": 311,
			"sectionTime": 9
		},
		{
			"fanSpeed": 7,
			"targetTemp": 315,
			"sectionTime": 9
		},
		{
			"fanSpeed": 7,
			"targetTemp": 318,
			"sectionTime": 9
		},
		{
			"fanSpeed": 7,
			"targetTemp": 321,
			"sectionTime": 9
		},
		{
			"fanSpeed": 6,
			"targetTemp": 324,
			"sectionTime": 9
		},
		{
			"fanSpeed": 6,
			"targetTemp": 328,
			"sectionTime": 9
		},
		{
			"fanSpeed": 6,
			"targetTemp": 321,
			"sectionTime": 9
		},
		{
			"fanSpeed": 6,
			"targetTemp": 334,
			"sectionTime": 9
		},
		{
			"fanSpeed": 6,
			"targetTemp": 338,
			"sectionTime": 9
		},
		{
			"fanSpeed": 6,
			"targetTemp": 341,
			"sectionTime": 9
		},
		{
			"fanSpeed": 6,
			"targetTemp": 344,
			"sectionTime": 9
		},
		{
			"fanSpeed": 6,
			"targetTemp": 348,
			"sectionTime": 9
		},
		{
			"fanSpeed": 6,
			"targetTemp": 351,
			"sectionTime": 9
		},
		{
			"fanSpeed": 5,
			"targetTemp": 354,
			"sectionTime": 9
		},
		{
			"fanSpeed": 5,
			"targetTemp": 357,
			"sectionTime": 9
		},
		{
			"fanSpeed": 5,
			"targetTemp": 361,
			"sectionTime": 9
		},
		{
			"fanSpeed": 5,
			"targetTemp": 364,
			"sectionTime": 9
		},
		{
			"fanSpeed": 5,
			"targetTemp": 367,
			"sectionTime": 9
		},
		{
			"fanSpeed": 5,
			"targetTemp": 371,
			"sectionTime": 9
		},
		{
			"fanSpeed": 5,
			"targetTemp": 373,
			"sectionTime": 9
		},
		{
			"fanSpeed": 5,
			"targetTemp": 375,
			"sectionTime": 9
		},
		{
			"fanSpeed": 5,
			"targetTemp": 378,
			"sectionTime": 9
		},
		{
			"fanSpeed": 6,
			"targetTemp": 380,
			"sectionTime": 9
		},
		{
			"fanSpeed": 6,
			"targetTemp": 382,
			"sectionTime": 9
		},
		{
			"fanSpeed": 6,
			"targetTemp": 384,
			"sectionTime": 9
		},
		{
			"fanSpeed": 6,
			"targetTemp": 387,
			"sectionTime": 9
		},
		{
			"fanSpeed": 6,
			"targetTemp": 389,
			"sectionTime": 9
		},
		{
			"fanSpeed": 6,
			"targetTemp": 391,
			"sectionTime": 9
		},
		{
			"fanSpeed": 6,
			"targetTemp": 394,
			"sectionTime": 9
		},
		{
			"fanSpeed": 6,
			"targetTemp": 396,
			"sectionTime": 9
		},
		{
			"fanSpeed": 6,
			"targetTemp": 398,
			"sectionTime": 9
		},
		{
			"fanSpeed": 7,
			"targetTemp": 400,
			"sectionTime": 9
		},
		{
			"fanSpeed": 7,
			"targetTemp": 403,
			"sectionTime": 9
		},
		{
			"fanSpeed": 7,
			"targetTemp": 405,
			"sectionTime": 9
		},
		{
			"fanSpeed": 7,
			"targetTemp": 407,
			"sectionTime": 9
		},
		{
			"fanSpeed": 7,
			"targetTemp": 410,
			"sectionTime": 9
		},
		{
			"fanSpeed": 7,
			"targetTemp": 412,
			"sectionTime": 9
		},
		{
			"fanSpeed": 7,
			"targetTemp": 414,
			"sectionTime": 9
		},
		{
			"fanSpeed": 7,
			"targetTemp": 417,
			"sectionTime": 9
		},
		{
			"fanSpeed": 7,
			"targetTemp": 420,
			"sectionTime": 9
		},
		{
			"fanSpeed": 7,
			"targetTemp": 423,
			"sectionTime": 9
		},
		{
			"fanSpeed": 7,
			"targetTemp": 426,
			"sectionTime": 9
		},
		{
			"fanSpeed": 7,
			"targetTemp": 430,
			"sectionTime": 9
		},
		{
			"fanSpeed": 7,
			"targetTemp": 433,
			"sectionTime": 9
		},
		{
			"fanSpeed": 7,
			"targetTemp": 436,
			"sectionTime": 9
		},
		{
			"fanSpeed": 7,
			"targetTemp": 440,
			"sectionTime": 9
		},
		{
			"fanSpeed": 7,
			"targetTemp": 443,
			"sectionTime": 9
		},
		{
			"fanSpeed": 7,
			"targetTemp": 446,
			"sectionTime": 9
		},
		{
			"fanSpeed": 7,
			"targetTemp": 450,
			"sectionTime": 9
		},
        {
            "cooling": true,
            "fanSpeed": 9,
            "sectionTime": 180
        }
    ],
    "totalTime": 964,
    "roastDescription": {
        "description": "",
        "roastType": ""
    },
    "bean": {
        "country": "",
        "source": {
            "reseller": "",
            "link": ""
        },
        "region": ""
    },
    "roastName": "cat-cloud style v4",
    "creator": ""
}